[{"template_name": "squad_v2", "template_number": "1", "metrics": {"general_accuracy": 81.6667, "exact_recalls_disease name": 40.796, "exact_recalls_location": 30.3665, "exact_recalls_date": 13.6752, "exact_recalls_%CI values": 13.3333, "exact_recalls_method": 13.7363, "exact_recalls_R0 value": 21.5116, "exact_recalls_overall": 22.2365, "partial_recalls_disease name": 41.791, "partial_recalls_location": 32.9843, "partial_recalls_date": 24.7863, "partial_recalls_%CI values": 31.6667, "partial_recalls_method": 14.8352, "partial_recalls_R0 value": 27.7372, "partial_recalls_overall": 28.9668, "exact_precisions_disease name": 49.697, "exact_precisions_location": 42.963, "exact_precisions_date": 24.2424, "exact_precisions_%CI values": 23.5294, "exact_precisions_method": 21.3675, "exact_precisions_R0 value": 33.0357, "exact_precisions_overall": 32.4725, "partial_precisions_disease name": 50.9091, "partial_precisions_location": 46.6667, "partial_precisions_date": 43.9394, "partial_precisions_%CI values": 55.8824, "partial_precisions_method": 23.0769, "partial_precisions_R0 value": 46.0606, "partial_precisions_overall": 44.4225, "exact_f1s_disease name": 44.8087, "exact_f1s_location": 35.5828, "exact_f1s_date": 17.4863, "exact_f1s_%CI values": 17.0213, "exact_f1s_method": 16.7224, "exact_f1s_R0 value": 26.0563, "exact_f1s_overall": 26.3969, "partial_f1s_disease name": 45.9016, "partial_f1s_location": 38.6503, "partial_f1s_date": 31.694, "partial_f1s_%CI values": 40.4255, "partial_f1s_method": 18.0602, "partial_f1s_R0 value": 34.6241, "partial_f1s_overall": 35.0672, "rouge1": 68.595, "rouge2": 21.955, "rougeL": 68.2844, "rougeLsum": 68.3679}}, {"template_name": "squad_v2", "template_number": "2", "metrics": {"general_accuracy": 81.3333, "exact_recalls_disease name": 38.3085, "exact_recalls_location": 28.7958, "exact_recalls_date": 13.6752, "exact_recalls_%CI values": 13.3333, "exact_recalls_method": 12.0879, "exact_recalls_R0 value": 22.6744, "exact_recalls_overall": 21.4792, "partial_recalls_disease name": 39.801, "partial_recalls_location": 30.8901, "partial_recalls_date": 24.7863, "partial_recalls_%CI values": 26.6667, "partial_recalls_method": 13.7363, "partial_recalls_R0 value": 27.3723, "partial_recalls_overall": 27.2088, "exact_precisions_disease name": 46.9512, "exact_precisions_location": 41.9847, "exact_precisions_date": 25.3968, "exact_precisions_%CI values": 23.5294, "exact_precisions_method": 17.7419, "exact_precisions_R0 value": 35.1351, "exact_precisions_overall": 31.7899, "partial_precisions_disease name": 48.7805, "partial_precisions_location": 45.0382, "partial_precisions_date": 46.0317, "partial_precisions_%CI values": 47.0588, "partial_precisions_method": 20.1613, "partial_precisions_R0 value": 46.0123, "partial_precisions_overall": 42.1805, "exact_f1s_disease name": 42.1918, "exact_f1s_location": 34.1615, "exact_f1s_date": 17.7778, "exact_f1s_%CI values": 17.0213, "exact_f1s_method": 14.3791, "exact_f1s_R0 value": 27.5618, "exact_f1s_overall": 25.6367, "partial_f1s_disease name": 43.8356, "partial_f1s_location": 36.646, "partial_f1s_date": 32.2222, "partial_f1s_%CI values": 34.0426, "partial_f1s_method": 16.3399, "partial_f1s_R0 value": 34.3249, "partial_f1s_overall": 33.0794, "rouge1": 67.8099, "rouge2": 21.2057, "rougeL": 67.472, "rougeLsum": 67.605}}, {"template_name": "squad_v2", "template_number": "4", "metrics": {"general_accuracy": 82.6667, "exact_recalls_disease name": 40.796, "exact_recalls_location": 29.8429, "exact_recalls_date": 12.8205, "exact_recalls_%CI values": 13.3333, "exact_recalls_method": 13.7363, "exact_recalls_R0 value": 22.6744, "exact_recalls_overall": 22.2006, "partial_recalls_disease name": 41.791, "partial_recalls_location": 32.4607, "partial_recalls_date": 23.0769, "partial_recalls_%CI values": 30.0, "partial_recalls_method": 14.8352, "partial_recalls_R0 value": 27.3723, "partial_recalls_overall": 28.256, "exact_precisions_disease name": 50.0, "exact_precisions_location": 43.1818, "exact_precisions_date": 23.4375, "exact_precisions_%CI values": 21.0526, "exact_precisions_method": 21.1864, "exact_precisions_R0 value": 33.913, "exact_precisions_overall": 32.1286, "partial_precisions_disease name": 51.2195, "partial_precisions_location": 46.9697, "partial_precisions_date": 42.1875, "partial_precisions_%CI values": 47.3684, "partial_precisions_method": 22.8814, "partial_precisions_R0 value": 45.4545, "partial_precisions_overall": 42.6802, "exact_f1s_disease name": 44.9315, "exact_f1s_location": 35.2941, "exact_f1s_date": 16.5746, "exact_f1s_%CI values": 16.3265, "exact_f1s_method": 16.6667, "exact_f1s_R0 value": 27.1777, "exact_f1s_overall": 26.2575, "partial_f1s_disease name": 46.0274, "partial_f1s_location": 38.3901, "partial_f1s_date": 29.8343, "partial_f1s_%CI values": 36.7347, "partial_f1s_method": 18.0, "partial_f1s_R0 value": 34.1686, "partial_f1s_overall": 34.0016, "rouge1": 69.8802, "rouge2": 22.2041, "rougeL": 69.6224, "rougeLsum": 69.6007}}, {"template_name": "squad_v2", "template_number": "5", "metrics": {"general_accuracy": 81.6667, "exact_recalls_disease name": 41.2935, "exact_recalls_location": 29.8429, "exact_recalls_date": 12.8205, "exact_recalls_%CI values": 13.3333, "exact_recalls_method": 13.7363, "exact_recalls_R0 value": 21.5116, "exact_recalls_overall": 22.0897, "partial_recalls_disease name": 42.2886, "partial_recalls_location": 31.9372, "partial_recalls_date": 24.7863, "partial_recalls_%CI values": 30.0, "partial_recalls_method": 15.9341, "partial_recalls_R0 value": 27.7372, "partial_recalls_overall": 28.7806, "exact_precisions_disease name": 48.8235, "exact_precisions_location": 41.9118, "exact_precisions_date": 23.0769, "exact_precisions_%CI values": 22.2222, "exact_precisions_method": 20.1613, "exact_precisions_R0 value": 31.8966, "exact_precisions_overall": 31.3487, "partial_precisions_disease name": 50.0, "partial_precisions_location": 44.8529, "partial_precisions_date": 44.6154, "partial_precisions_%CI values": 50.0, "partial_precisions_method": 23.3871, "partial_precisions_R0 value": 42.6966, "partial_precisions_overall": 42.592, "exact_f1s_disease name": 44.7439, "exact_f1s_location": 34.8624, "exact_f1s_date": 16.4835, "exact_f1s_%CI values": 16.6667, "exact_f1s_method": 16.3399, "exact_f1s_R0 value": 25.6944, "exact_f1s_overall": 25.9171, "partial_f1s_disease name": 45.8221, "partial_f1s_location": 37.3089, "partial_f1s_date": 31.8681, "partial_f1s_%CI values": 37.5, "partial_f1s_method": 18.9542, "partial_f1s_R0 value": 33.6283, "partial_f1s_overall": 34.3499, "rouge1": 68.7607, "rouge2": 22.3, "rougeL": 68.3482, "rougeLsum": 68.4405}}, {"template_name": "squad_v2", "template_number": "6", "metrics": {"general_accuracy": 81.6667, "exact_recalls_disease name": 40.2985, "exact_recalls_location": 29.3194, "exact_recalls_date": 13.6752, "exact_recalls_%CI values": 13.3333, "exact_recalls_method": 13.7363, "exact_recalls_R0 value": 21.5116, "exact_recalls_overall": 21.9791, "partial_recalls_disease name": 41.2935, "partial_recalls_location": 31.4136, "partial_recalls_date": 25.641, "partial_recalls_%CI values": 30.0, "partial_recalls_method": 15.9341, "partial_recalls_R0 value": 27.7372, "partial_recalls_overall": 28.6699, "exact_precisions_disease name": 49.3902, "exact_precisions_location": 42.1053, "exact_precisions_date": 24.6154, "exact_precisions_%CI values": 23.5294, "exact_precisions_method": 21.0084, "exact_precisions_R0 value": 32.7434, "exact_precisions_overall": 32.232, "partial_precisions_disease name": 50.6098, "partial_precisions_location": 45.1128, "partial_precisions_date": 46.1538, "partial_precisions_%CI values": 52.9412, "partial_precisions_method": 24.3697, "partial_precisions_R0 value": 43.4286, "partial_precisions_overall": 43.7693, "exact_f1s_disease name": 44.3836, "exact_f1s_location": 34.5679, "exact_f1s_date": 17.5824, "exact_f1s_%CI values": 17.0213, "exact_f1s_method": 16.6113, "exact_f1s_R0 value": 25.9649, "exact_f1s_overall": 26.136, "partial_f1s_disease name": 45.4795, "partial_f1s_location": 37.037, "partial_f1s_date": 32.967, "partial_f1s_%CI values": 38.2979, "partial_f1s_method": 19.2691, "partial_f1s_R0 value": 33.853, "partial_f1s_overall": 34.6459, "rouge1": 69.051, "rouge2": 22.0059, "rougeL": 68.8026, "rougeLsum": 68.8043}}, {"template_name": "squad_v2", "template_number": "7", "metrics": {"general_accuracy": 81.6667, "exact_recalls_disease name": 40.796, "exact_recalls_location": 29.8429, "exact_recalls_date": 12.8205, "exact_recalls_%CI values": 13.3333, "exact_recalls_method": 13.7363, "exact_recalls_R0 value": 22.093, "exact_recalls_overall": 22.1037, "partial_recalls_disease name": 41.791, "partial_recalls_location": 31.9372, "partial_recalls_date": 24.7863, "partial_recalls_%CI values": 30.0, "partial_recalls_method": 15.3846, "partial_recalls_R0 value": 28.1022, "partial_recalls_overall": 28.6669, "exact_precisions_disease name": 48.2353, "exact_precisions_location": 41.9118, "exact_precisions_date": 23.0769, "exact_precisions_%CI values": 22.2222, "exact_precisions_method": 20.3252, "exact_precisions_R0 value": 32.7586, "exact_precisions_overall": 31.4217, "partial_precisions_disease name": 49.4118, "partial_precisions_location": 44.8529, "partial_precisions_date": 44.6154, "partial_precisions_%CI values": 50.0, "partial_precisions_method": 22.7642, "partial_precisions_R0 value": 43.75, "partial_precisions_overall": 42.5657, "exact_f1s_disease name": 44.2049, "exact_f1s_location": 34.8624, "exact_f1s_date": 16.4835, "exact_f1s_%CI values": 16.6667, "exact_f1s_method": 16.3934, "exact_f1s_R0 value": 26.3889, "exact_f1s_overall": 25.9516, "partial_f1s_disease name": 45.283, "partial_f1s_location": 37.3089, "partial_f1s_date": 31.8681, "partial_f1s_%CI values": 37.5, "partial_f1s_method": 18.3607, "partial_f1s_R0 value": 34.2222, "partial_f1s_overall": 34.2603, "rouge1": 68.6399, "rouge2": 22.2124, "rougeL": 68.2162, "rougeLsum": 68.3559}}, {"template_name": "squad_v2", "template_number": "8", "metrics": {"general_accuracy": 83.0, "exact_recalls_disease name": 40.796, "exact_recalls_location": 30.3665, "exact_recalls_date": 12.8205, "exact_recalls_%CI values": 13.3333, "exact_recalls_method": 13.1868, "exact_recalls_R0 value": 22.093, "exact_recalls_overall": 22.0994, "partial_recalls_disease name": 41.791, "partial_recalls_location": 32.9843, "partial_recalls_date": 23.9316, "partial_recalls_%CI values": 30.0, "partial_recalls_method": 14.2857, "partial_recalls_R0 value": 27.3723, "partial_recalls_overall": 28.3942, "exact_precisions_disease name": 50.3067, "exact_precisions_location": 44.2748, "exact_precisions_date": 23.4375, "exact_precisions_%CI values": 21.0526, "exact_precisions_method": 20.5128, "exact_precisions_R0 value": 33.0435, "exact_precisions_overall": 32.1047, "partial_precisions_disease name": 51.5337, "partial_precisions_location": 48.0916, "partial_precisions_date": 43.75, "partial_precisions_%CI values": 47.3684, "partial_precisions_method": 22.2222, "partial_precisions_R0 value": 45.1807, "partial_precisions_overall": 43.0245, "exact_f1s_disease name": 45.0549, "exact_f1s_location": 36.0248, "exact_f1s_date": 16.5746, "exact_f1s_%CI values": 16.3265, "exact_f1s_method": 16.0535, "exact_f1s_R0 value": 26.4808, "exact_f1s_overall": 26.1786, "partial_f1s_disease name": 46.1538, "partial_f1s_location": 39.1304, "partial_f1s_date": 30.9392, "partial_f1s_%CI values": 36.7347, "partial_f1s_method": 17.3913, "partial_f1s_R0 value": 34.0909, "partial_f1s_overall": 34.2108, "rouge1": 70.034, "rouge2": 22.3806, "rougeL": 69.7593, "rougeLsum": 69.7702}}, {"template_name": "squad_v2", "template_number": "9", "metrics": {"general_accuracy": 81.0, "exact_recalls_disease name": 38.806, "exact_recalls_location": 29.3194, "exact_recalls_date": 13.6752, "exact_recalls_%CI values": 13.3333, "exact_recalls_method": 13.1868, "exact_recalls_R0 value": 20.9302, "exact_recalls_overall": 21.5418, "partial_recalls_disease name": 39.801, "partial_recalls_location": 31.9372, "partial_recalls_date": 23.9316, "partial_recalls_%CI values": 26.6667, "partial_recalls_method": 14.2857, "partial_recalls_R0 value": 27.7372, "partial_recalls_overall": 27.3932, "exact_precisions_disease name": 48.4472, "exact_precisions_location": 43.0769, "exact_precisions_date": 24.6154, "exact_precisions_%CI values": 25.0, "exact_precisions_method": 20.6897, "exact_precisions_R0 value": 32.4324, "exact_precisions_overall": 32.3769, "partial_precisions_disease name": 49.6894, "partial_precisions_location": 46.9231, "partial_precisions_date": 43.0769, "partial_precisions_%CI values": 50.0, "partial_precisions_method": 22.4138, "partial_precisions_R0 value": 44.4444, "partial_precisions_overall": 42.7579, "exact_f1s_disease name": 43.0939, "exact_f1s_location": 34.891, "exact_f1s_date": 17.5824, "exact_f1s_%CI values": 17.3913, "exact_f1s_method": 16.1074, "exact_f1s_R0 value": 25.4417, "exact_f1s_overall": 25.8707, "partial_f1s_disease name": 44.1989, "partial_f1s_location": 38.0062, "partial_f1s_date": 30.7692, "partial_f1s_%CI values": 34.7826, "partial_f1s_method": 17.4497, "partial_f1s_R0 value": 34.1573, "partial_f1s_overall": 33.393, "rouge1": 67.8861, "rouge2": 21.6705, "rougeL": 67.6747, "rougeLsum": 67.6707}}, {"template_name": "squad_v2", "template_number": "10", "metrics": {"general_accuracy": 82.0, "exact_recalls_disease name": 38.806, "exact_recalls_location": 29.3194, "exact_recalls_date": 12.8205, "exact_recalls_%CI values": 13.3333, "exact_recalls_method": 13.7363, "exact_recalls_R0 value": 20.3488, "exact_recalls_overall": 21.394, "partial_recalls_disease name": 39.801, "partial_recalls_location": 31.4136, "partial_recalls_date": 23.9316, "partial_recalls_%CI values": 26.6667, "partial_recalls_method": 15.9341, "partial_recalls_R0 value": 27.0073, "partial_recalls_overall": 27.459, "exact_precisions_disease name": 47.561, "exact_precisions_location": 42.4242, "exact_precisions_date": 23.8095, "exact_precisions_%CI values": 23.5294, "exact_precisions_method": 20.6612, "exact_precisions_R0 value": 30.9735, "exact_precisions_overall": 31.4931, "partial_precisions_disease name": 48.7805, "partial_precisions_location": 45.4545, "partial_precisions_date": 44.4444, "partial_precisions_%CI values": 47.0588, "partial_precisions_method": 23.9669, "partial_precisions_R0 value": 42.2857, "partial_precisions_overall": 41.9985, "exact_f1s_disease name": 42.7397, "exact_f1s_location": 34.6749, "exact_f1s_date": 16.6667, "exact_f1s_%CI values": 17.0213, "exact_f1s_method": 16.5017, "exact_f1s_R0 value": 24.5614, "exact_f1s_overall": 25.4794, "partial_f1s_disease name": 43.8356, "partial_f1s_location": 37.1517, "partial_f1s_date": 31.1111, "partial_f1s_%CI values": 34.0426, "partial_f1s_method": 19.1419, "partial_f1s_R0 value": 32.9621, "partial_f1s_overall": 33.207, "rouge1": 68.8055, "rouge2": 21.7613, "rougeL": 68.538, "rougeLsum": 68.5517}}, {"template_name": "drop", "template_number": "1", "metrics": {"general_accuracy": 82.0, "exact_recalls_disease name": 38.806, "exact_recalls_location": 29.3194, "exact_recalls_date": 12.8205, "exact_recalls_%CI values": 13.3333, "exact_recalls_method": 13.1868, "exact_recalls_R0 value": 22.6744, "exact_recalls_overall": 21.6901, "partial_recalls_disease name": 39.801, "partial_recalls_location": 31.4136, "partial_recalls_date": 23.9316, "partial_recalls_%CI values": 30.0, "partial_recalls_method": 14.2857, "partial_recalls_R0 value": 27.7372, "partial_recalls_overall": 27.8615, "exact_precisions_disease name": 46.7066, "exact_precisions_location": 41.4815, "exact_precisions_date": 23.0769, "exact_precisions_%CI values": 21.0526, "exact_precisions_method": 19.8347, "exact_precisions_R0 value": 33.6207, "exact_precisions_overall": 30.9622, "partial_precisions_disease name": 47.9042, "partial_precisions_location": 44.4444, "partial_precisions_date": 43.0769, "partial_precisions_%CI values": 47.3684, "partial_precisions_method": 21.4876, "partial_precisions_R0 value": 45.2381, "partial_precisions_overall": 41.5866, "exact_f1s_disease name": 42.3913, "exact_f1s_location": 34.3558, "exact_f1s_date": 16.4835, "exact_f1s_%CI values": 16.3265, "exact_f1s_method": 15.8416, "exact_f1s_R0 value": 27.0833, "exact_f1s_overall": 25.5097, "partial_f1s_disease name": 43.4783, "partial_f1s_location": 36.8098, "partial_f1s_date": 30.7692, "partial_f1s_%CI values": 36.7347, "partial_f1s_method": 17.1617, "partial_f1s_R0 value": 34.3891, "partial_f1s_overall": 33.3678, "rouge1": 68.4784, "rouge2": 21.7955, "rougeL": 68.1465, "rougeLsum": 68.173}}, {"template_name": "drop", "template_number": "2", "metrics": {"general_accuracy": 81.6667, "exact_recalls_disease name": 41.2935, "exact_recalls_location": 30.3665, "exact_recalls_date": 12.8205, "exact_recalls_%CI values": 13.3333, "exact_recalls_method": 14.2857, "exact_recalls_R0 value": 22.093, "exact_recalls_overall": 22.3654, "partial_recalls_disease name": 42.2886, "partial_recalls_location": 32.4607, "partial_recalls_date": 24.7863, "partial_recalls_%CI values": 30.0, "partial_recalls_method": 15.9341, "partial_recalls_R0 value": 28.4672, "partial_recalls_overall": 28.9895, "exact_precisions_disease name": 47.9769, "exact_precisions_location": 41.4286, "exact_precisions_date": 22.0588, "exact_precisions_%CI values": 21.0526, "exact_precisions_method": 20.6349, "exact_precisions_R0 value": 31.9328, "exact_precisions_overall": 30.8474, "partial_precisions_disease name": 49.1329, "partial_precisions_location": 44.2857, "partial_precisions_date": 42.6471, "partial_precisions_%CI values": 47.3684, "partial_precisions_method": 23.0159, "partial_precisions_R0 value": 43.5754, "partial_precisions_overall": 41.6709, "exact_f1s_disease name": 44.385, "exact_f1s_location": 35.0453, "exact_f1s_date": 16.2162, "exact_f1s_%CI values": 16.3265, "exact_f1s_method": 16.8831, "exact_f1s_R0 value": 26.1168, "exact_f1s_overall": 25.9304, "partial_f1s_disease name": 45.4545, "partial_f1s_location": 37.4622, "partial_f1s_date": 31.3514, "partial_f1s_%CI values": 36.7347, "partial_f1s_method": 18.8312, "partial_f1s_R0 value": 34.4371, "partial_f1s_overall": 34.1922, "rouge1": 68.712, "rouge2": 22.2021, "rougeL": 68.3278, "rougeLsum": 68.3919}}, {"template_name": "drop", "template_number": "3", "metrics": {"general_accuracy": 82.0, "exact_recalls_disease name": 41.2935, "exact_recalls_location": 30.3665, "exact_recalls_date": 12.8205, "exact_recalls_%CI values": 13.3333, "exact_recalls_method": 14.2857, "exact_recalls_R0 value": 22.6744, "exact_recalls_overall": 22.4623, "partial_recalls_disease name": 42.2886, "partial_recalls_location": 32.4607, "partial_recalls_date": 24.7863, "partial_recalls_%CI values": 30.0, "partial_recalls_method": 15.3846, "partial_recalls_R0 value": 28.1022, "partial_recalls_overall": 28.8371, "exact_precisions_disease name": 48.8235, "exact_precisions_location": 42.029, "exact_precisions_date": 22.3881, "exact_precisions_%CI values": 21.0526, "exact_precisions_method": 20.9677, "exact_precisions_R0 value": 33.0508, "exact_precisions_overall": 31.3853, "partial_precisions_disease name": 50.0, "partial_precisions_location": 44.9275, "partial_precisions_date": 43.2836, "partial_precisions_%CI values": 47.3684, "partial_precisions_method": 22.5806, "partial_precisions_R0 value": 45.2941, "partial_precisions_overall": 42.2424, "exact_f1s_disease name": 44.7439, "exact_f1s_location": 35.2584, "exact_f1s_date": 16.3043, "exact_f1s_%CI values": 16.3265, "exact_f1s_method": 16.9935, "exact_f1s_R0 value": 26.8966, "exact_f1s_overall": 26.1845, "partial_f1s_disease name": 45.8221, "partial_f1s_location": 37.69, "partial_f1s_date": 31.5217, "partial_f1s_%CI values": 36.7347, "partial_f1s_method": 18.3007, "partial_f1s_R0 value": 34.6847, "partial_f1s_overall": 34.2756, "rouge1": 68.8931, "rouge2": 22.1877, "rougeL": 68.5744, "rougeLsum": 68.674}}, {"template_name": "drop", "template_number": "4", "metrics": {"general_accuracy": 81.6667, "exact_recalls_disease name": 41.2935, "exact_recalls_location": 30.3665, "exact_recalls_date": 12.8205, "exact_recalls_%CI values": 13.3333, "exact_recalls_method": 14.2857, "exact_recalls_R0 value": 22.093, "exact_recalls_overall": 22.3654, "partial_recalls_disease name": 42.2886, "partial_recalls_location": 32.4607, "partial_recalls_date": 24.7863, "partial_recalls_%CI values": 30.0, "partial_recalls_method": 15.9341, "partial_recalls_R0 value": 28.4672, "partial_recalls_overall": 28.9895, "exact_precisions_disease name": 47.9769, "exact_precisions_location": 41.4286, "exact_precisions_date": 22.0588, "exact_precisions_%CI values": 21.0526, "exact_precisions_method": 20.6349, "exact_precisions_R0 value": 31.9328, "exact_precisions_overall": 30.8474, "partial_precisions_disease name": 49.1329, "partial_precisions_location": 44.2857, "partial_precisions_date": 42.6471, "partial_precisions_%CI values": 47.3684, "partial_precisions_method": 23.0159, "partial_precisions_R0 value": 43.5754, "partial_precisions_overall": 41.6709, "exact_f1s_disease name": 44.385, "exact_f1s_location": 35.0453, "exact_f1s_date": 16.2162, "exact_f1s_%CI values": 16.3265, "exact_f1s_method": 16.8831, "exact_f1s_R0 value": 26.1168, "exact_f1s_overall": 25.9304, "partial_f1s_disease name": 45.4545, "partial_f1s_location": 37.4622, "partial_f1s_date": 31.3514, "partial_f1s_%CI values": 36.7347, "partial_f1s_method": 18.8312, "partial_f1s_R0 value": 34.4371, "partial_f1s_overall": 34.1922, "rouge1": 68.7102, "rouge2": 22.2791, "rougeL": 68.3781, "rougeLsum": 68.4559}}, {"template_name": "drop", "template_number": "5", "metrics": {"general_accuracy": 82.0, "exact_recalls_disease name": 40.796, "exact_recalls_location": 30.3665, "exact_recalls_date": 12.8205, "exact_recalls_%CI values": 13.3333, "exact_recalls_method": 13.1868, "exact_recalls_R0 value": 22.6744, "exact_recalls_overall": 22.1963, "partial_recalls_disease name": 41.791, "partial_recalls_location": 32.9843, "partial_recalls_date": 23.0769, "partial_recalls_%CI values": 30.0, "partial_recalls_method": 14.2857, "partial_recalls_R0 value": 27.3723, "partial_recalls_overall": 28.2517, "exact_precisions_disease name": 49.3976, "exact_precisions_location": 43.2836, "exact_precisions_date": 22.7273, "exact_precisions_%CI values": 21.0526, "exact_precisions_method": 19.8347, "exact_precisions_R0 value": 33.913, "exact_precisions_overall": 31.7015, "partial_precisions_disease name": 50.6024, "partial_precisions_location": 47.0149, "partial_precisions_date": 40.9091, "partial_precisions_%CI values": 47.3684, "partial_precisions_method": 21.4876, "partial_precisions_R0 value": 46.2963, "partial_precisions_overall": 42.2798, "exact_f1s_disease name": 44.6866, "exact_f1s_location": 35.6923, "exact_f1s_date": 16.3934, "exact_f1s_%CI values": 16.3265, "exact_f1s_method": 15.8416, "exact_f1s_R0 value": 27.1777, "exact_f1s_overall": 26.1107, "partial_f1s_disease name": 45.7766, "partial_f1s_location": 38.7692, "partial_f1s_date": 29.5082, "partial_f1s_%CI values": 36.7347, "partial_f1s_method": 17.1617, "partial_f1s_R0 value": 34.4037, "partial_f1s_overall": 33.8707, "rouge1": 69.1265, "rouge2": 22.4406, "rougeL": 68.8355, "rougeLsum": 68.8648}}, {"template_name": "drop", "template_number": "6", "metrics": {"general_accuracy": 82.0, "exact_recalls_disease name": 40.2985, "exact_recalls_location": 30.3665, "exact_recalls_date": 12.8205, "exact_recalls_%CI values": 13.3333, "exact_recalls_method": 14.2857, "exact_recalls_R0 value": 20.9302, "exact_recalls_overall": 22.0058, "partial_recalls_disease name": 41.2935, "partial_recalls_location": 32.4607, "partial_recalls_date": 24.7863, "partial_recalls_%CI values": 26.6667, "partial_recalls_method": 15.3846, "partial_recalls_R0 value": 27.7372, "partial_recalls_overall": 28.0548, "exact_precisions_disease name": 47.6471, "exact_precisions_location": 42.3358, "exact_precisions_date": 22.3881, "exact_precisions_%CI values": 22.2222, "exact_precisions_method": 20.8, "exact_precisions_R0 value": 30.7692, "exact_precisions_overall": 31.0271, "partial_precisions_disease name": 48.8235, "partial_precisions_location": 45.2555, "partial_precisions_date": 43.2836, "partial_precisions_%CI values": 44.4444, "partial_precisions_method": 22.4, "partial_precisions_R0 value": 42.9379, "partial_precisions_overall": 41.1908, "exact_f1s_disease name": 43.6658, "exact_f1s_location": 35.3659, "exact_f1s_date": 16.3043, "exact_f1s_%CI values": 16.6667, "exact_f1s_method": 16.9381, "exact_f1s_R0 value": 24.9135, "exact_f1s_overall": 25.7491, "partial_f1s_disease name": 44.7439, "partial_f1s_location": 37.8049, "partial_f1s_date": 31.5217, "partial_f1s_%CI values": 33.3333, "partial_f1s_method": 18.241, "partial_f1s_R0 value": 33.7029, "partial_f1s_overall": 33.3769, "rouge1": 68.7556, "rouge2": 22.0135, "rougeL": 68.446, "rougeLsum": 68.5044}}, {"template_name": "drop", "template_number": "7", "metrics": {"general_accuracy": 82.6667, "exact_recalls_disease name": 40.2985, "exact_recalls_location": 30.3665, "exact_recalls_date": 12.8205, "exact_recalls_%CI values": 15.0, "exact_recalls_method": 13.7363, "exact_recalls_R0 value": 22.093, "exact_recalls_overall": 22.3858, "partial_recalls_disease name": 41.2935, "partial_recalls_location": 32.9843, "partial_recalls_date": 23.0769, "partial_recalls_%CI values": 28.3333, "partial_recalls_method": 15.3846, "partial_recalls_R0 value": 28.8321, "partial_recalls_overall": 28.3175, "exact_precisions_disease name": 48.503, "exact_precisions_location": 42.963, "exact_precisions_date": 23.4375, "exact_precisions_%CI values": 24.3243, "exact_precisions_method": 20.4918, "exact_precisions_R0 value": 32.4786, "exact_precisions_overall": 32.033, "partial_precisions_disease name": 49.7006, "partial_precisions_location": 46.6667, "partial_precisions_date": 42.1875, "partial_precisions_%CI values": 45.9459, "partial_precisions_method": 22.9508, "partial_precisions_R0 value": 45.4023, "partial_precisions_overall": 42.1423, "exact_f1s_disease name": 44.0217, "exact_f1s_location": 35.5828, "exact_f1s_date": 16.5746, "exact_f1s_%CI values": 18.5567, "exact_f1s_method": 16.4474, "exact_f1s_R0 value": 26.2976, "exact_f1s_overall": 26.3543, "partial_f1s_disease name": 45.1087, "partial_f1s_location": 38.6503, "partial_f1s_date": 29.8343, "partial_f1s_%CI values": 35.0515, "partial_f1s_method": 18.4211, "partial_f1s_R0 value": 35.2679, "partial_f1s_overall": 33.8736, "rouge1": 69.7596, "rouge2": 22.3304, "rougeL": 69.345, "rougeLsum": 69.4742}}]